badauth/__init__.py
badauth/_version.py
badauth/common/__init__.py
badauth/common/clientauthalgo.py
badauth/common/constants.py
badauth/common/credentials/__init__.py
badauth/common/credentials/credssp.py
badauth/common/credentials/kerberos.py
badauth/common/credentials/ntlm.py
badauth/common/credentials/spnego.py
badauth/common/credentials/spnegoex.py
badauth/common/subprotocols/__init__.py
badauth/common/subprotocols/custom.py
badauth/common/subprotocols/native.py
badauth/common/subprotocols/sspi.py
badauth/common/subprotocols/sspiproxy.py
badauth/common/subprotocols/wsnet.py
badauth/common/subprotocols/wsnetdirect.py
badauth/common/winapi/__init__.py
badauth/common/winapi/constants.py
badauth/common/winapi/functiondefs.py
badauth/common/winapi/token.py
badauth/common/winapi/winsspi.py
badauth/protocols/__init__.py
badauth/protocols/credssp/__init__.py
badauth/protocols/credssp/client/__init__.py
badauth/protocols/credssp/client/native.py
badauth/protocols/credssp/messages/__init__.py
badauth/protocols/credssp/messages/asn1_structs.py
badauth/protocols/credssp/messages/remcredguard.py
badauth/protocols/kerberos/__init__.py
badauth/protocols/kerberos/gssapi.py
badauth/protocols/kerberos/gssapismb.py
badauth/protocols/kerberos/client/__init__.py
badauth/protocols/kerberos/client/native.py
badauth/protocols/kerberos/client/sspi.py
badauth/protocols/kerberos/client/sspiproxy.py
badauth/protocols/kerberos/client/wsnet.py
badauth/protocols/kerberos/client/wsnetdirect.py
badauth/protocols/ntlm/__init__.py
badauth/protocols/ntlm/creds_calc.py
badauth/protocols/ntlm/client/__init__.py
badauth/protocols/ntlm/client/native.py
badauth/protocols/ntlm/client/sspi.py
badauth/protocols/ntlm/client/sspiproxy.py
badauth/protocols/ntlm/client/wsnet.py
badauth/protocols/ntlm/client/wsnetdirect.py
badauth/protocols/ntlm/messages/__init__.py
badauth/protocols/ntlm/messages/authenticate.py
badauth/protocols/ntlm/messages/challenge.py
badauth/protocols/ntlm/messages/negotiate.py
badauth-0.1.5.dist-info/licenses/LICENSE
badauth-0.1.5.dist-info/METADATA
badauth-0.1.5.dist-info/WHEEL
badauth-0.1.5.dist-info/top_level.txt
badauth-0.1.5.dist-info/RECORD
